pypi_pronounce.py
pypi_pronounce-0.0.0.1.dist-info/RECORD
pypi_pronounce-0.0.0.1.dist-info/top_level.txt
pypi_pronounce-0.0.0.1.dist-info/WHEEL
pypi_pronounce-0.0.0.1.dist-info/METADATA
