Metadata-Version: 2.0
Name: pypi-pronounce
Version: 0.0.0.1
Summary: A user-friendly guide to pronouncing PyPI.
Home-page: http://pypi.python.org/
Author: Jean-Paul Calderone
Author-email: exarkun@twistedmatrix.com
License: UNKNOWN
Platform: UNKNOWN
